{
    "lang": "fr",
    "joumouaaTime": "13:15",
    "aidTime": "",
    "imsakNbMinBeforeSobh": 0,
    "minimumIchaTime": "18:50",
    "maximumIchaTimeForNoWaiting": "22:00",
    "prayersWaitingTimes": [10, 10, 10, 5, 10],
    "prayerTimesFixing": ["", "", "", "", ""],
    "hijriAdjustment": 0,
    "hijriDateEnabled": true,
    "douaaAfterAdhanEnabled": true,
    "douaaAfterPrayerEnabled": true,
    "androidAppEnabled": false,
    "calculChoice": "custom",
    "city": "null",
    "prayerMethod": "ISNA",
    "latitude": "",
    "longitude": "",
    "fajrDegree": "15",
    "ichaaDegree": "15",
    "sobhAdjust": 0,
    "dohrAdjust": 0,
    "asrAdjust": 0,
    "maghribAdjust": 0,
    "ishaAdjust": 0,
    "iqamaDisplayTime": 45,
    "adhanDouaaDisplayTime": 30,
    "headerText": "",
    "site": "",
    "supportTel": "sobh et ichaa sont calculé sur l'angle de 15°",
    "footerText": ""
}
